azure/mgmt/newrelicobservability/__init__.py
azure/mgmt/newrelicobservability/_configuration.py
azure/mgmt/newrelicobservability/_new_relic_observability_mgmt_client.py
azure/mgmt/newrelicobservability/_patch.py
azure/mgmt/newrelicobservability/_serialization.py
azure/mgmt/newrelicobservability/_vendor.py
azure/mgmt/newrelicobservability/_version.py
azure/mgmt/newrelicobservability/py.typed
azure/mgmt/newrelicobservability/aio/__init__.py
azure/mgmt/newrelicobservability/aio/_configuration.py
azure/mgmt/newrelicobservability/aio/_new_relic_observability_mgmt_client.py
azure/mgmt/newrelicobservability/aio/_patch.py
azure/mgmt/newrelicobservability/aio/operations/__init__.py
azure/mgmt/newrelicobservability/aio/operations/_accounts_operations.py
azure/mgmt/newrelicobservability/aio/operations/_billing_info_operations.py
azure/mgmt/newrelicobservability/aio/operations/_connected_partner_resources_operations.py
azure/mgmt/newrelicobservability/aio/operations/_monitored_subscriptions_operations.py
azure/mgmt/newrelicobservability/aio/operations/_monitors_operations.py
azure/mgmt/newrelicobservability/aio/operations/_operations.py
azure/mgmt/newrelicobservability/aio/operations/_organizations_operations.py
azure/mgmt/newrelicobservability/aio/operations/_patch.py
azure/mgmt/newrelicobservability/aio/operations/_plans_operations.py
azure/mgmt/newrelicobservability/aio/operations/_tag_rules_operations.py
azure/mgmt/newrelicobservability/models/__init__.py
azure/mgmt/newrelicobservability/models/_models_py3.py
azure/mgmt/newrelicobservability/models/_new_relic_observability_mgmt_client_enums.py
azure/mgmt/newrelicobservability/models/_patch.py
azure/mgmt/newrelicobservability/operations/__init__.py
azure/mgmt/newrelicobservability/operations/_accounts_operations.py
azure/mgmt/newrelicobservability/operations/_billing_info_operations.py
azure/mgmt/newrelicobservability/operations/_connected_partner_resources_operations.py
azure_mgmt_newrelicobservability-1.1.0.dist-info/LICENSE
azure_mgmt_newrelicobservability-1.1.0.dist-info/METADATA
azure_mgmt_newrelicobservability-1.1.0.dist-info/WHEEL
azure_mgmt_newrelicobservability-1.1.0.dist-info/top_level.txt
azure_mgmt_newrelicobservability-1.1.0.dist-info/RECORD
